maildrake/__init__.py
maildrake/_metadata.py
maildrake/config.py
maildrake/message.py
maildrake/smtp/__init__.py
maildrake/smtp/__main__.py
maildrake/smtp/service.py
maildrake/smtp/tests/__init__.py
maildrake/smtp/tests/test_service.py
maildrake/store/__init__.py
maildrake/store/__main__.py
maildrake/store/fixture.sql
maildrake/store/manage.py
maildrake/store/schema.sql
maildrake/store/sqlite.py
maildrake/store/tests/__init__.py
maildrake/store/tests/test_manage.py
maildrake/store/tests/test_sqlite.py
maildrake/tests/__init__.py
maildrake/tests/test_message.py
maildrake/tests/test_metadata.py
maildrake/tests/test_smtp.py
maildrake/tests/test_store.py
maildrake/web/__init__.py
maildrake/web/__main__.py
maildrake/web/service.py
maildrake/web/views.py
maildrake/web/static/images/maildrake.png
maildrake/web/templates/index.html
maildrake/web/templates/layout.html
maildrake/web/templates/login.html
maildrake/web/templates/message_detail.html
maildrake/web/templates/message_list.html
maildrake/web/tests/__init__.py
maildrake/web/tests/test_service.py
maildrake/web/tests/test_views.py
maildrake-0.1.8.dist-info/DESCRIPTION.rst
maildrake-0.1.8.dist-info/METADATA
maildrake-0.1.8.dist-info/RECORD
maildrake-0.1.8.dist-info/WHEEL
maildrake-0.1.8.dist-info/entry_points.txt
maildrake-0.1.8.dist-info/metadata.json
maildrake-0.1.8.dist-info/top_level.txt
