Metadata-Version: 2.0
Name: maildrake
Version: 0.1.8
Summary: Development tool for testing email traffic.
Home-page: https://pagure.io/maildrake/
Author: Ben Finney
Author-email: ben+python@benfinney.id.au
License: GNU AGPL-3+
Keywords: email,smtp,queue,debug
Platform: UNKNOWN
Classifier: Development Status :: 4 - Beta
Classifier: License :: OSI Approved :: GNU Affero General Public License v3 or later (AGPLv3+)
Classifier: Operating System :: POSIX
Classifier: Programming Language :: Python :: 3.2
Classifier: Programming Language :: Python :: 3.3
Classifier: Programming Language :: Python :: 3.4
Classifier: Programming Language :: Python :: 3.5
Classifier: Programming Language :: Python :: 3.6
Classifier: Intended Audience :: Developers
Classifier: Intended Audience :: System Administrators
Classifier: Topic :: Communications :: Email :: Mail Transport Agents
Classifier: Topic :: Software Development :: Testing
Requires-Dist: Flask
Requires-Dist: docutils
Requires-Dist: fasteners
Requires-Dist: semver
Requires-Dist: setuptools
Requires-Dist: sqlparse
